{
"type": "FeatureCollection",
"name": "SOUTH BOSTON",
"crs": { "type": "name", "properties": { "name": "urn:ogc:def:crs:OGC:1.3:CRS84" } },
"features": [
{ "type": "Feature", "properties": { "Name": "CVS PHARMACY 0979", "description": "<html>\n<iframe scrolling=\"yes\" name=\"ReportFrame\" id=\"ReportFrame\" align=\"top\" frameborder= \"0\" \n      MARGINWIDTH=\"0\" MARGINHEIGHT=\"0\" \n      width=\"350px\" height=\"400px\" \n      src=\"http:\/\/iaspub.epa.gov\/enviro\/national_kml.registry_html?p_registry_id=110043184069\"><\/iframe>\n<br>\n<\/font><\/body><\/html>" }, "geometry": { "type": "Point", "coordinates": [ -71.04754, 42.33669 ] } }
]
}
